drop.py
drop_cli-1.2.dist-info/METADATA
drop_cli-1.2.dist-info/WHEEL
drop_cli-1.2.dist-info/entry_points.txt
drop_cli-1.2.dist-info/top_level.txt
drop_cli-1.2.dist-info/RECORD
