Metadata-Version: 2.1
Name: drop-cli
Version: 1.2
Summary: UNKNOWN
Home-page: https://github.com/Bobrinik/drop
Author: Maksim Bober
License: UNKNOWN
Platform: UNKNOWN
Requires-Dist: click
